{
  "class": "lock",
  "images": {
    "large": "{{driverAssetsPath}}/images/large.jpg",
    "small": "{{driverAssetsPath}}/images/small.jpg"
  },
  "icon": "{{driverAssetsPath}}/icon.svg",
  "pair": [
    {
      "id": "query_nuki_servers",
      "$template": "query_nuki_servers"
    },
    {
      "id": "select_bridge",
      "$template": "select_bridge"
    },
    {
      "id": "query_bridge",
      "$template": "query_bridge"
    },
    {
      "id": "manual_pairing",
      "$template": "manual_pairing"
    },
    {
      "id": "list_devices",
      "template": "list_devices",
      "navigation": {
        "next": "add_devices"
      }
    },
    {
      "id": "add_devices",
      "template": "add_devices"
    }
  ]
}
